mjlib
